limepy/__init__.py
limepy/download.py
limepy/wrangle.py
limepy-0.1.15.dist-info/licenses/LICENSE
limepy-0.1.15.dist-info/METADATA
limepy-0.1.15.dist-info/WHEEL
limepy-0.1.15.dist-info/top_level.txt
limepy-0.1.15.dist-info/RECORD
