Metadata-Version: 2.4
Name: limepy
Version: 0.1.15
Summary: Download, summarise and process LimeSurvey data
Home-page: https://codeberg.org/dirkmjk/limepy
Author: dirkmjk
Author-email: info@dirkmjk.nl
License: MIT
License-File: LICENSE
Requires-Dist: pandas
Requires-Dist: numpy
Requires-Dist: requests
Requires-Dist: xmltodict
Dynamic: author
Dynamic: author-email
Dynamic: description
Dynamic: description-content-type
Dynamic: home-page
Dynamic: license
Dynamic: license-file
Dynamic: requires-dist
Dynamic: summary
